deepkan/__init__.py
deepkan/deepkan.py
Deep_KAN-0.0.4.dist-info/METADATA
Deep_KAN-0.0.4.dist-info/WHEEL
Deep_KAN-0.0.4.dist-info/top_level.txt
Deep_KAN-0.0.4.dist-info/RECORD
